nnfs/__init__.py
nnfs/core.py
nnfs/console/__init__.py
nnfs/console/nnfs.py
nnfs/datasets/__init__.py
nnfs/datasets/sine.py
nnfs/datasets/spiral.py
nnfs/datasets/vertical.py
nnfs_video_tutorial_code/001.py
nnfs_video_tutorial_code/002.py
nnfs_video_tutorial_code/003.py
nnfs_video_tutorial_code/004.py
nnfs_video_tutorial_code/005.py
nnfs_video_tutorial_code/__init__.py
nnfs-0.5.1.dist-info/LICENSE
nnfs-0.5.1.dist-info/METADATA
nnfs-0.5.1.dist-info/WHEEL
nnfs-0.5.1.dist-info/entry_points.txt
nnfs-0.5.1.dist-info/top_level.txt
nnfs-0.5.1.dist-info/RECORD
